visier/__init__.py
visier/sdk/__init__.py
visier/sdk/api/__init__.py
visier/sdk/api/consolidated_analytics/__init__.py
visier/sdk/api/consolidated_analytics/api_client.py
visier/sdk/api/consolidated_analytics/api_response.py
visier/sdk/api/consolidated_analytics/configuration.py
visier/sdk/api/consolidated_analytics/exceptions.py
visier/sdk/api/consolidated_analytics/py.typed
visier/sdk/api/consolidated_analytics/rest.py
visier/sdk/api/consolidated_analytics/api/__init__.py
visier/sdk/api/consolidated_analytics/api/consolidated_analytics_v1_alpha_api.py
visier/sdk/api/consolidated_analytics/models/__init__.py
visier/sdk/api/consolidated_analytics/models/consolidated_analytics_api_excluded_source_list_dto.py
visier/sdk/api/consolidated_analytics/models/consolidated_analytics_api_source_tenant_list_dto.py
visier/sdk/api/consolidated_analytics/models/consolidated_analytics_api_tenant_create_request_dto.py
visier/sdk/api/consolidated_analytics/models/consolidated_analytics_api_tenant_list_response_dto.py
visier/sdk/api/consolidated_analytics/models/consolidated_analytics_api_tenant_with_details.py
visier/sdk/api/consolidated_analytics/models/consolidated_analytics_api_tenant_with_details_list_response_dto.py
visier/sdk/api/consolidated_analytics/models/excluded_sources_body.py
visier/sdk/api/consolidated_analytics/models/google_protobuf_any.py
visier/sdk/api/consolidated_analytics/models/status.py
visier/sdk/api/consolidated_analytics/models/tenant_code_body.py
visier.sdk.api.consolidated_analytics-0.0.4.dist-info/METADATA
visier.sdk.api.consolidated_analytics-0.0.4.dist-info/WHEEL
visier.sdk.api.consolidated_analytics-0.0.4.dist-info/top_level.txt
visier.sdk.api.consolidated_analytics-0.0.4.dist-info/RECORD
